smash_tourney/__init__.py
smash_tourney/smash_tourney.py
smash_tourney-0.2.0.dist-info/LICENSE
smash_tourney-0.2.0.dist-info/METADATA
smash_tourney-0.2.0.dist-info/WHEEL
smash_tourney-0.2.0.dist-info/entry_points.txt
smash_tourney-0.2.0.dist-info/top_level.txt
smash_tourney-0.2.0.dist-info/RECORD
