Metadata-Version: 2.1
Name: smash-tourney
Version: 0.2.0
Summary: The Open Source Super Smash Bros. 1v1 randomizer with customizable "versus" voice implementer!
Home-page: https://github.com/rnegron/smash-tourney
Author: Raúl Negrón
Author-email: raul@raulnegron.me
License: MIT
Platform: UNKNOWN
Classifier: Environment :: Console
Classifier: License :: OSI Approved :: MIT License
Classifier: Development Status :: 4 - Beta
Classifier: Topic :: Games/Entertainment
Classifier: Topic :: Multimedia :: Sound/Audio :: Speech
Classifier: Programming Language :: Python
Classifier: Programming Language :: Python :: 3
Classifier: Programming Language :: Python :: 3.6
Classifier: Programming Language :: Python :: Implementation :: CPython
Requires-Python: >=3.6.0
Requires-Dist: pydub
Requires-Dist: gTTS
